audit_themis_i18n/__init__.py
audit_themis_i18n-2.3.5.dist-info/METADATA
audit_themis_i18n-2.3.5.dist-info/WHEEL
audit_themis_i18n-2.3.5.dist-info/top_level.txt
audit_themis_i18n-2.3.5.dist-info/RECORD
