Metadata-Version: 2.1
Name: audit-themis-i18n
Version: 2.3.5
Summary: test
Author: serverinspector2
Author-email: serverinspector+2@wearehackerone.com
Requires-Dist: requests
